{"states": {"LAX": {"city_code": "LAX", "enabled": true, "req_cutoff": 14, "require_declining": false, "dsm_time": null, "dsm_high": null, "dsm_source": "DSM", "effective_cutoff": 21, "max_known": 59.0, "wethr_high": 59.0, "wethr_high_cutoff": "2026-03-28 00:00:00", "reliable_max": 59.0, "newest_cutoff_time": "2026-03-28 06:20:00", "mos_declining": true, "_declining_cutoff": 14, "_declining_check_ts": 1774703206.8625689, "elim_bucket_range": null, "elim_bucket_yes_ask": null, "win_prob_at_report": null, "ask_at_report": null, "bucket_range": null, "bucket_ticker": null, "win_prob_at_bet": null, "cost_basis": null, "contracts": null, "avg_price": null, "order_id": null, "current_value": null, "profit": null, "local_date": "2026-03-28", "bet_placed": false, "error": null}, "SEA": {"city_code": "SEA", "enabled": true, "req_cutoff": 15, "require_declining": false, "dsm_time": null, "dsm_high": null, "dsm_source": "6hr", "effective_cutoff": 21, "max_known": 46.4, "wethr_high": 46.0, "wethr_high_cutoff": "2026-03-28 00:00:00", "reliable_max": 46.0, "newest_cutoff_time": "2026-03-28 06:20:00", "mos_declining": false, "_declining_cutoff": 15, "_declining_check_ts": 1774703207.059508, "elim_bucket_range": null, "elim_bucket_yes_ask": null, "win_prob_at_report": null, "ask_at_report": null, "bucket_range": null, "bucket_ticker": null, "win_prob_at_bet": null, "cost_basis": null, "contracts": null, "avg_price": null, "order_id": null, "current_value": null, "profit": null, "local_date": "2026-03-28", "bet_placed": false, "error": null}, "MIA": {"city_code": "MIA", "enabled": true, "req_cutoff": 15, "require_declining": false, "dsm_time": null, "dsm_high": null, "dsm_source": "DSM", "effective_cutoff": 18, "max_known": 75.2, "wethr_high": 75.0, "wethr_high_cutoff": "2026-03-28 08:10:00", "reliable_max": 75.0, "newest_cutoff_time": "2026-03-28 09:20:00", "mos_declining": true, "_declining_cutoff": 15, "_declining_check_ts": 1774703395.789262, "elim_bucket_range": null, "elim_bucket_yes_ask": null, "win_prob_at_report": null, "ask_at_report": null, "bucket_range": null, "bucket_ticker": null, "win_prob_at_bet": null, "cost_basis": null, "contracts": null, "avg_price": null, "order_id": null, "current_value": null, "profit": null, "local_date": "2026-03-28", "bet_placed": false, "error": null}, "CHI": {"city_code": "CHI", "enabled": true, "req_cutoff": 15, "require_declining": false, "dsm_time": null, "dsm_high": null, "dsm_source": "DSM", "effective_cutoff": 23, "max_known": 33.8, "wethr_high": 33.0, "wethr_high_cutoff": "2026-03-28 00:00:00", "reliable_max": 33.1, "newest_cutoff_time": "2026-03-28 08:20:00", "mos_declining": false, "_declining_cutoff": 15, "_declining_check_ts": 1774703332.2307, "elim_bucket_range": null, "elim_bucket_yes_ask": null, "win_prob_at_report": null, "ask_at_report": null, "bucket_range": null, "bucket_ticker": null, "win_prob_at_bet": null, "cost_basis": null, "contracts": null, "avg_price": null, "order_id": null, "current_value": null, "profit": null, "local_date": "2026-03-28", "bet_placed": false, "error": null}, "ATL": {"city_code": "ATL", "enabled": true, "req_cutoff": 16, "require_declining": false, "dsm_time": null, "dsm_high": null, "dsm_source": "6hr", "effective_cutoff": 19, "max_known": 60.8, "wethr_high": 60.0, "wethr_high_cutoff": "2026-03-28 00:00:00", "reliable_max": 60.0, "newest_cutoff_time": "2026-03-28 09:20:00", "mos_declining": true, "_declining_cutoff": 16, "_declining_check_ts": 1774703395.9744809, "elim_bucket_range": null, "elim_bucket_yes_ask": null, "win_prob_at_report": null, "ask_at_report": null, "bucket_range": null, "bucket_ticker": null, "win_prob_at_bet": null, "cost_basis": null, "contracts": null, "avg_price": null, "order_id": null, "current_value": null, "profit": null, "local_date": "2026-03-28", "bet_placed": false, "error": null}, "NYC": {"city_code": "NYC", "enabled": true, "req_cutoff": 15, "require_declining": false, "dsm_time": null, "dsm_high": null, "dsm_source": "DSM", "effective_cutoff": 18, "max_known": 39.0, "wethr_high": 39.0, "wethr_high_cutoff": "2026-03-28 00:51:00", "reliable_max": 39.0, "newest_cutoff_time": "2026-03-28 08:51:00", "mos_declining": false, "_declining_cutoff": 15, "_declining_check_ts": 1774703396.0881972, "elim_bucket_range": null, "elim_bucket_yes_ask": null, "win_prob_at_report": null, "ask_at_report": null, "bucket_range": null, "bucket_ticker": null, "win_prob_at_bet": null, "cost_basis": null, "contracts": null, "avg_price": null, "order_id": null, "current_value": null, "profit": null, "local_date": "2026-03-28", "bet_placed": false, "error": null}, "HOU": {"city_code": "HOU", "enabled": true, "req_cutoff": 15, "require_declining": false, "dsm_time": null, "dsm_high": null, "dsm_source": "DSM", "effective_cutoff": 23, "max_known": 72.0, "wethr_high": 72.0, "wethr_high_cutoff": "2026-03-28 01:22:00", "reliable_max": 72.0, "newest_cutoff_time": "2026-03-28 08:20:00", "mos_declining": false, "_declining_cutoff": 15, "_declining_check_ts": 1774703333.741139, "elim_bucket_range": null, "elim_bucket_yes_ask": null, "win_prob_at_report": null, "ask_at_report": null, "bucket_range": null, "bucket_ticker": null, "win_prob_at_bet": null, "cost_basis": null, "contracts": null, "avg_price": null, "order_id": null, "current_value": null, "profit": null, "local_date": "2026-03-28", "bet_placed": false, "error": null}, "AUS": {"city_code": "AUS", "enabled": true, "req_cutoff": 16, "require_declining": false, "dsm_time": null, "dsm_high": null, "dsm_source": "DSM", "effective_cutoff": 23, "max_known": 60.8, "wethr_high": 60.0, "wethr_high_cutoff": "2026-03-28 00:00:00", "reliable_max": 60.1, "newest_cutoff_time": "2026-03-28 08:20:00", "mos_declining": false, "_declining_cutoff": 16, "_declining_check_ts": 1774703333.891606, "elim_bucket_range": null, "elim_bucket_yes_ask": null, "win_prob_at_report": null, "ask_at_report": null, "bucket_range": null, "bucket_ticker": null, "win_prob_at_bet": null, "cost_basis": null, "contracts": null, "avg_price": null, "order_id": null, "current_value": null, "profit": null, "local_date": "2026-03-28", "bet_placed": false, "error": null}, "DCA": {"city_code": "DCA", "enabled": true, "req_cutoff": 16, "require_declining": false, "dsm_time": null, "dsm_high": null, "dsm_source": "DSM", "effective_cutoff": 18, "max_known": 42.8, "wethr_high": 42.0, "wethr_high_cutoff": "2026-03-28 00:00:00", "reliable_max": 42.0, "newest_cutoff_time": "2026-03-28 09:20:00", "mos_declining": false, "_declining_cutoff": 16, "_declining_check_ts": 1774703396.216815, "elim_bucket_range": null, "elim_bucket_yes_ask": null, "win_prob_at_report": null, "ask_at_report": null, "bucket_range": null, "bucket_ticker": null, "win_prob_at_bet": null, "cost_basis": null, "contracts": null, "avg_price": null, "order_id": null, "current_value": null, "profit": null, "local_date": "2026-03-28", "bet_placed": false, "error": null}, "PHX": {"city_code": "PHX", "enabled": true, "req_cutoff": 16, "require_declining": false, "dsm_time": null, "dsm_high": null, "dsm_source": "DSM", "effective_cutoff": 22, "max_known": 81.0, "wethr_high": 81.0, "wethr_high_cutoff": "2026-03-28 03:51:00", "reliable_max": 81.0, "newest_cutoff_time": "2026-03-28 06:20:00", "mos_declining": false, "_declining_cutoff": 16, "_declining_check_ts": 1774703268.7695181, "elim_bucket_range": null, "elim_bucket_yes_ask": null, "win_prob_at_report": null, "ask_at_report": null, "bucket_range": null, "bucket_ticker": null, "win_prob_at_bet": null, "cost_basis": null, "contracts": null, "avg_price": null, "order_id": null, "current_value": null, "profit": null, "local_date": "2026-03-28", "bet_placed": false, "error": null}, "DEN": {"city_code": "DEN", "enabled": true, "req_cutoff": 15, "require_declining": false, "dsm_time": null, "dsm_high": null, "dsm_source": "6hr", "effective_cutoff": 22, "max_known": 40.0, "wethr_high": 40.0, "wethr_high_cutoff": "2026-03-28 00:53:00", "reliable_max": 40.0, "newest_cutoff_time": "2026-03-28 07:20:00", "mos_declining": false, "_declining_cutoff": 15, "_declining_check_ts": 1774703268.97536, "elim_bucket_range": null, "elim_bucket_yes_ask": null, "win_prob_at_report": null, "ask_at_report": null, "bucket_range": null, "bucket_ticker": null, "win_prob_at_bet": null, "cost_basis": null, "contracts": null, "avg_price": null, "order_id": null, "current_value": null, "profit": null, "local_date": "2026-03-28", "bet_placed": false, "error": null}, "BOS": {"city_code": "BOS", "enabled": true, "req_cutoff": 15, "require_declining": false, "dsm_time": null, "dsm_high": null, "dsm_source": "DSM", "effective_cutoff": 19, "max_known": 32.0, "wethr_high": 32.0, "wethr_high_cutoff": "2026-03-28 00:00:00", "reliable_max": 32.0, "newest_cutoff_time": "2026-03-28 09:20:00", "mos_declining": true, "_declining_cutoff": 15, "_declining_check_ts": 1774703396.371885, "elim_bucket_range": null, "elim_bucket_yes_ask": null, "win_prob_at_report": null, "ask_at_report": null, "bucket_range": null, "bucket_ticker": null, "win_prob_at_bet": null, "cost_basis": null, "contracts": null, "avg_price": null, "order_id": null, "current_value": null, "profit": null, "local_date": "2026-03-28", "bet_placed": false, "error": null}, "PHL": {"city_code": "PHL", "enabled": true, "req_cutoff": 15, "require_declining": false, "dsm_time": null, "dsm_high": null, "dsm_source": "DSM", "effective_cutoff": 18, "max_known": 41.0, "wethr_high": 41.0, "wethr_high_cutoff": "2026-03-28 00:00:00", "reliable_max": 41.0, "newest_cutoff_time": "2026-03-28 09:20:00", "mos_declining": false, "_declining_cutoff": 15, "_declining_check_ts": 1774703396.5046542, "elim_bucket_range": null, "elim_bucket_yes_ask": null, "win_prob_at_report": null, "ask_at_report": null, "bucket_range": null, "bucket_ticker": null, "win_prob_at_bet": null, "cost_basis": null, "contracts": null, "avg_price": null, "order_id": null, "current_value": null, "profit": null, "local_date": "2026-03-28", "bet_placed": false, "error": null}, "LAS": {"city_code": "LAS", "enabled": true, "req_cutoff": 16, "require_declining": false, "dsm_time": null, "dsm_high": null, "dsm_source": "DSM", "effective_cutoff": 21, "max_known": 73.4, "wethr_high": 73.0, "wethr_high_cutoff": "2026-03-28 00:00:00", "reliable_max": 73.0, "newest_cutoff_time": "2026-03-28 06:20:00", "mos_declining": true, "_declining_cutoff": 16, "_declining_check_ts": 1774703207.247026, "elim_bucket_range": null, "elim_bucket_yes_ask": null, "win_prob_at_report": null, "ask_at_report": null, "bucket_range": null, "bucket_ticker": null, "win_prob_at_bet": null, "cost_basis": null, "contracts": null, "avg_price": null, "order_id": null, "current_value": null, "profit": null, "local_date": "2026-03-28", "bet_placed": false, "error": null}, "SFO": {"city_code": "SFO", "enabled": true, "req_cutoff": 16, "require_declining": false, "dsm_time": null, "dsm_high": null, "dsm_source": "DSM", "effective_cutoff": 21, "max_known": 55.4, "wethr_high": 55.0, "wethr_high_cutoff": "2026-03-28 00:00:00", "reliable_max": 55.0, "newest_cutoff_time": "2026-03-28 06:20:00", "mos_declining": false, "_declining_cutoff": 16, "_declining_check_ts": 1774703207.4042351, "elim_bucket_range": null, "elim_bucket_yes_ask": null, "win_prob_at_report": null, "ask_at_report": null, "bucket_range": null, "bucket_ticker": null, "win_prob_at_bet": null, "cost_basis": null, "contracts": null, "avg_price": null, "order_id": null, "current_value": null, "profit": null, "local_date": "2026-03-28", "bet_placed": false, "error": null}, "OKC": {"city_code": "OKC", "enabled": true, "req_cutoff": 16, "require_declining": false, "dsm_time": null, "dsm_high": null, "dsm_source": "DSM", "effective_cutoff": 23, "max_known": 53.6, "wethr_high": 53.0, "wethr_high_cutoff": "2026-03-28 00:00:00", "reliable_max": 53.0, "newest_cutoff_time": "2026-03-28 08:20:00", "mos_declining": false, "_declining_cutoff": 16, "_declining_check_ts": 1774703334.0403829, "elim_bucket_range": null, "elim_bucket_yes_ask": null, "win_prob_at_report": null, "ask_at_report": null, "bucket_range": null, "bucket_ticker": null, "win_prob_at_bet": null, "cost_basis": null, "contracts": null, "avg_price": null, "order_id": null, "current_value": null, "profit": null, "local_date": "2026-03-28", "bet_placed": false, "error": null}, "DFW": {"city_code": "DFW", "enabled": true, "req_cutoff": 15, "require_declining": false, "dsm_time": null, "dsm_high": null, "dsm_source": "DSM", "effective_cutoff": 23, "max_known": 56.0, "wethr_high": 56.0, "wethr_high_cutoff": "2026-03-28 00:53:00", "reliable_max": 56.0, "newest_cutoff_time": "2026-03-28 08:20:00", "mos_declining": true, "_declining_cutoff": 15, "_declining_check_ts": 1774703334.154115, "elim_bucket_range": null, "elim_bucket_yes_ask": null, "win_prob_at_report": null, "ask_at_report": null, "bucket_range": null, "bucket_ticker": null, "win_prob_at_bet": null, "cost_basis": null, "contracts": null, "avg_price": null, "order_id": null, "current_value": null, "profit": null, "local_date": "2026-03-28", "bet_placed": false, "error": null}, "NOL": {"city_code": "NOL", "enabled": true, "req_cutoff": 15, "require_declining": false, "dsm_time": null, "dsm_high": null, "dsm_source": "DSM", "effective_cutoff": 23, "max_known": 72, "wethr_high": 72.0, "wethr_high_cutoff": "2026-03-28 07:00:00", "reliable_max": 72, "newest_cutoff_time": "2026-03-28 08:20:00", "mos_declining": false, "_declining_cutoff": 15, "_declining_check_ts": 1774703334.27194, "elim_bucket_range": "L71", "elim_bucket_yes_ask": 1, "win_prob_at_report": null, "ask_at_report": null, "bucket_range": null, "bucket_ticker": null, "win_prob_at_bet": null, "cost_basis": null, "contracts": null, "avg_price": null, "order_id": null, "current_value": null, "profit": null, "local_date": "2026-03-28", "bet_placed": false, "error": null}, "MSP": {"city_code": "MSP", "enabled": true, "req_cutoff": 15, "require_declining": false, "dsm_time": null, "dsm_high": null, "dsm_source": "DSM", "effective_cutoff": 23, "max_known": 24.8, "wethr_high": 24.0, "wethr_high_cutoff": "2026-03-28 00:00:00", "reliable_max": 24.1, "newest_cutoff_time": "2026-03-28 08:20:00", "mos_declining": false, "_declining_cutoff": 15, "_declining_check_ts": 1774703334.383329, "elim_bucket_range": null, "elim_bucket_yes_ask": null, "win_prob_at_report": null, "ask_at_report": null, "bucket_range": null, "bucket_ticker": null, "win_prob_at_bet": null, "cost_basis": null, "contracts": null, "avg_price": null, "order_id": null, "current_value": null, "profit": null, "local_date": "2026-03-28", "bet_placed": false, "error": null}, "SAT": {"city_code": "SAT", "enabled": true, "req_cutoff": 16, "require_declining": false, "dsm_time": null, "dsm_high": null, "dsm_source": "DSM", "effective_cutoff": 23, "max_known": 57.2, "wethr_high": 57.0, "wethr_high_cutoff": "2026-03-28 00:00:00", "reliable_max": 57.0, "newest_cutoff_time": "2026-03-28 08:20:00", "mos_declining": false, "_declining_cutoff": 16, "_declining_check_ts": 1774703334.50607, "elim_bucket_range": null, "elim_bucket_yes_ask": null, "win_prob_at_report": null, "ask_at_report": null, "bucket_range": null, "bucket_ticker": null, "win_prob_at_bet": null, "cost_basis": null, "contracts": null, "avg_price": null, "order_id": null, "current_value": null, "profit": null, "local_date": "2026-03-28", "bet_placed": false, "error": null}}, "local_times": {"LAX": "6:27 AM", "SEA": "6:27 AM", "MIA": "9:27 AM", "CHI": "8:27 AM", "ATL": "9:27 AM", "NYC": "9:27 AM", "HOU": "8:27 AM", "AUS": "8:27 AM", "DCA": "9:27 AM", "PHX": "6:27 AM", "DEN": "7:27 AM", "BOS": "9:27 AM", "PHL": "9:27 AM", "LAS": "6:27 AM", "SFO": "6:27 AM", "OKC": "8:27 AM", "DFW": "8:27 AM", "NOL": "8:27 AM", "MSP": "8:27 AM", "SAT": "8:27 AM"}, "lst_times": {"LAX": "5:27 AM", "SEA": "5:27 AM", "MIA": "8:27 AM", "CHI": "7:27 AM", "ATL": "8:27 AM", "NYC": "8:27 AM", "HOU": "7:27 AM", "AUS": "7:27 AM", "DCA": "8:27 AM", "PHX": "6:27 AM", "DEN": "6:27 AM", "BOS": "8:27 AM", "PHL": "8:27 AM", "LAS": "5:27 AM", "SFO": "5:27 AM", "OKC": "7:27 AM", "DFW": "7:27 AM", "NOL": "7:27 AM", "MSP": "7:27 AM", "SAT": "7:27 AM"}, "max_date": "2026-03-28"}